psqlpandas/__init__.py
psqlpandas/__version__.py
psqlpandas/postgresql.py
psqlpandas/scripts/script.py
psqlpandas/tables.py
psqlpandas-1.6.4.dist-info/LICENSE
psqlpandas-1.6.4.dist-info/METADATA
psqlpandas-1.6.4.dist-info/WHEEL
psqlpandas-1.6.4.dist-info/RECORD
